main.py
agent/__init__.py
agent/base_agent.py
agent/bible_agent.py
agent/search_agent.py
agent/components/__init__.py
agent/components/goal_system.py
agent/components/learner.py
agent/components/memory.py
agent/components/planner.py
agent/components/session.py
config/__init__.py
config/settings.py
models/__init__.py
models/verse.py
models/verse_categories.py
services/__init__.py
services/model_manager.py
services/serper_service.py
services/llm/__init__.py
services/llm/base_llm.py
services/llm/gemini_llm.py
services/llm/hf_llm.py
services/llm/model_selector.py
services/llm/model_types.py
utils/__init__.py
utils/helpers.py
utils/verse_analytics.py
utils/formatters/__init__.py
utils/formatters/base_formatter.py
utils/formatters/console_formatter.py
utils/formatters/markdown_formatter.py
biblia-0.6.0.dist-info/LICENSE
biblia-0.6.0.dist-info/METADATA
biblia-0.6.0.dist-info/WHEEL
biblia-0.6.0.dist-info/entry_points.txt
biblia-0.6.0.dist-info/top_level.txt
biblia-0.6.0.dist-info/RECORD
