Metadata-Version: 2.2
Name: biblia
Version: 0.6.0
Summary: Bible Study Assistant for Christian Education and Research
Home-page: https://github.com/ashioyajotham/bible
Author: Victor Jotham Ashioya
Author-email: victorashioya960@gmail.com
Keywords: bible,ai,research,spirituality,education,assistant
Classifier: Development Status :: 4 - Beta
Classifier: Intended Audience :: Education
Classifier: Intended Audience :: Religion
Classifier: License :: OSI Approved :: MIT License
Classifier: Programming Language :: Python :: 3
Classifier: Programming Language :: Python :: 3.8
Classifier: Programming Language :: Python :: 3.9
Classifier: Programming Language :: Python :: 3.10
Classifier: Topic :: Religion
Classifier: Topic :: Education
Classifier: Topic :: Scientific/Engineering :: Artificial Intelligence
Requires-Python: >=3.8
License-File: LICENSE
Requires-Dist: requests>=2.30.0
Requires-Dist: python-dotenv>=1.0.0
Requires-Dist: google-generativeai>=0.3.0
Requires-Dist: colorama>=0.4.6
Requires-Dist: transformers>=4.30.0
Requires-Dist: torch>=2.0.0
Requires-Dist: accelerate>=0.20.0
Requires-Dist: rich>=12.0.0
Dynamic: author
Dynamic: author-email
Dynamic: classifier
Dynamic: description
Dynamic: description-content-type
Dynamic: home-page
Dynamic: keywords
Dynamic: requires-dist
Dynamic: requires-python
Dynamic: summary
